setup.py
news/__init__.py
news/settings.py
news/urls.py
news/wsgi.py
newsmodule/__init__.py
newsmodule/admin.py
newsmodule/api_views.py
newsmodule/apps.py
newsmodule/models.py
newsmodule/serializers.py
newsmodule/tests.py
newsmodule/urls.py
newsmodule/views.py
newsmodule.egg-info/PKG-INFO
newsmodule.egg-info/SOURCES.txt
newsmodule.egg-info/dependency_links.txt
newsmodule.egg-info/requires.txt
newsmodule.egg-info/top_level.txt
newsmodule/migrations/0001_initial.py
newsmodule/migrations/__init__.py
newsmodule/test_data/__init__.py
newsmodule/test_data/news.py