Metadata-Version: 1.0
Name: newsmodule
Version: 0.0.1
Summary: newsmodule log collection
Home-page: UNKNOWN
Author: cq
Author-email: chenq310@126.com
License: MIT License
Keywords: n,e,w,s,m,o,d,u,l,e
Platform: a
Platform: n
Platform: y
